ifmodel/__init__.py
ifmodel/ifconfig.py
ifmodel/ifheadmod.py
ifmodel/ifjobmod.py
ifmodel/iflinemod.py
ifmodel-1.2.1.dist-info/METADATA
ifmodel-1.2.1.dist-info/WHEEL
ifmodel-1.2.1.dist-info/top_level.txt
ifmodel-1.2.1.dist-info/RECORD
