Metadata-Version: 2.1
Name: ifmodel
Version: 1.2.1
Summary: A dataclass Collection that amisoftware use
Home-page: https://git.netsdl.com/chenchu/promotion-api
Author: chenchu
Author-email: chenchu@netsdl.com
License: MIT
Keywords: model python
Platform: UNKNOWN
